{
  "project_info": {
    "project_number": "476964627641",
    "project_id": "neuchatapp",
    "storage_bucket": "neuchatapp.appspot.com"
  },
  "client": [
    {
      "client_info": {
        "mobilesdk_app_id": "1:476964627641:android:876b52c3d353ea61df6768",
        "android_client_info": {
          "package_name": "com.example.chat_app"
        }
      },
      "oauth_client": [],
      "api_key": [
        {
          "current_key": "AIzaSyBMNyVhutKEa-SDh-N9rdtMCfhq9fwMnJQ"
        }
      ],
      "services": {
        "appinvite_service": {
          "other_platform_oauth_client": []
        }
      }
    }
  ],
  "configuration_version": "1"
}